cabot_check_ping/__init__.py
cabot_check_ping/models.py
cabot_check_ping/urls.py
cabot_check_ping/views.py
cabot_check_ping/migrations/0001_initial.py
cabot_check_ping/migrations/__init__.py
cabot_check_ping-0.1.1.dist-info/DESCRIPTION.rst
cabot_check_ping-0.1.1.dist-info/METADATA
cabot_check_ping-0.1.1.dist-info/RECORD
cabot_check_ping-0.1.1.dist-info/WHEEL
cabot_check_ping-0.1.1.dist-info/metadata.json
cabot_check_ping-0.1.1.dist-info/top_level.txt
