Metadata-Version: 2.0
Name: cabot-check-ping
Version: 0.1.1
Summary: A ping check plugin for Cabot
Home-page: https://github.com/decryptus/cabot-check-ping
Author: Adrien DELLE CAVE
Author-email: pypi@doowan.net
License: UNKNOWN
Platform: UNKNOWN
